pyls_pop/conf.py
pyls_pop/scripts.py
pyls_pop/version.py
pyls_pop/pyls_pop/cache.py
pyls_pop/pyls_pop/init.py
pyls_pop/pyls_pop/plugin.py
pyls_pop/pyls_pop/utils.py
pyls_pop-0.1.0.dist-info/LICENSE
pyls_pop-0.1.0.dist-info/METADATA
pyls_pop-0.1.0.dist-info/WHEEL
pyls_pop-0.1.0.dist-info/entry_points.txt
pyls_pop-0.1.0.dist-info/top_level.txt
pyls_pop-0.1.0.dist-info/RECORD
