Metadata-Version: 2.1
Name: pyls-pop
Version: 0.1.0
Summary: Python Language Server plugin for POP
Home-page: https://gitlab.com/saltstack/pop/pyls-pop
Author: VMWare
Author-email: engineering@vmware.com
License: UNKNOWN
Keywords: PyLSP,pop
Platform: UNKNOWN
Classifier: Environment :: Console
Classifier: Intended Audience :: Developers
Classifier: Intended Audience :: Information Technology
Classifier: Intended Audience :: System Administrators
Classifier: Operating System :: OS Independent
Classifier: Programming Language :: Python
Classifier: Programming Language :: Python :: 3.6
Classifier: Programming Language :: Python :: 3.7
Classifier: Programming Language :: Python :: 3.8
Classifier: Programming Language :: Python :: 3.9
Classifier: Development Status :: 5 - Production/Stable
Requires-Python: >=3.6
License-File: LICENSE
Requires-Dist: filelock
Requires-Dist: pop (>=17.0)
Requires-Dist: pop-tree
Requires-Dist: rend
Requires-Dist: python-lsp-server
